[
  {
    "id": 1,
    "question": "电影《肖申克的救赎》中，典狱长最后的结局是？",
    "answer": 4,
    "options": [
      "被谋杀",
      "被捕",
      "被审判",
      "自杀"
    ]
  },
  {
    "id": 2,
    "question": "「玉带林中挂，金簪雪里埋」是哪部文学作品中的描述？",
    "answer": 3,
    "options": [
      "水浒传",
      "金瓶梅",
      "红楼梦",
      "西厢记"
    ]
  },
  {
    "id": 3,
    "question": "「竹杖芒鞋轻胜马，谁怕，一蓑烟雨任平生轻」是谁的诗词？",
    "answer": 3,
    "options": [
      "苏小妹",
      "苏辙",
      "苏轼",
      "苏洵"
    ]
  },
  {
    "id": 4,
    "question": "《爱一个人好难》、《男人不该让女人流泪》是哪位歌手的代表歌曲？",
    "answer": 3,
    "options": [
      "林志炫",
      "张学友",
      "苏永康",
      "蔡康永"
    ]
  },
  {
    "id": 5,
    "question": "PP是什么物质的简称？",
    "answer": 1,
    "options": [
      "聚丙烯",
      "聚苯乙烯",
      "聚丁烯",
      "聚乙烯"
    ]
  },
  {
    "id": 6,
    "question": "牛顿通过什么水果发现了万有引力？",
    "answer": 2,
    "options": [
      "梨子",
      "苹果",
      "榴莲",
      "香蕉"
    ]
  },
  {
    "id": 7,
    "question": "刘备于哪一年称帝？",
    "answer": 3,
    "options": [
      "公元226年",
      "公元222年",
      "公元221年",
      "公元223年"
    ]
  },
  {
    "id": 8,
    "question": "以下哪位是唐宋八大家之一？",
    "answer": 2,
    "options": [
      "曾肇",
      "曾巩",
      "曾协",
      "曾布"
    ]
  },
  {
    "id": 9,
    "question": "细胞膜在物质通过时，具有什么性质？",
    "answer": 1,
    "options": [
      "半透性",
      "全透性",
      "选择透过性",
      "不允许物质通过"
    ]
  },
  {
    "id": 10,
    "question": "玻璃天花板指的是职场对下列哪种人群的歧视？",
    "answer": 1,
    "options": [
      "女性",
      "少年",
      "老人",
      "男性"
    ]
  },
  {
    "id": 11,
    "question": "以下哪项是美妆品牌YSL的译名？",
    "answer": 4,
    "options": [
      "杨树林",
      "圣兰黛",
      "以色列",
      "圣罗兰"
    ]
  },
  {
    "id": 12,
    "question": "染色体中决定男性性别的基因用哪个字母表示？",
    "answer": 1,
    "options": [
      "Y",
      "A",
      "X",
      "B"
    ]
  },
  {
    "id": 13,
    "question": "太阳最外层是？",
    "answer": 2,
    "options": [
      "光球层",
      "日冕层",
      "色球层",
      "大气层"
    ]
  },
  {
    "id": 14,
    "question": "以下哪种气体是惰性气体？",
    "answer": 2,
    "options": [
      "氢",
      "氦",
      "氧",
      "氮"
    ]
  },
  {
    "id": 15,
    "question": "5×5+5+5＝？",
    "answer": 1,
    "options": [
      "35",
      "25",
      "50",
      "30"
    ]
  },
  {
    "id": 16,
    "question": "电视剧《笑傲江湖》中，被东方不败篡位的日月神教教主是谁？",
    "answer": 2,
    "options": [
      "任盈盈",
      "任我行",
      "刘正风",
      "曲阳"
    ]
  },
  {
    "id": 17,
    "question": "微软Word软件中，用来搜索的快捷键是「ctrl」加上哪个字母键？",
    "answer": 1,
    "options": [
      "F",
      "C",
      "B",
      "V"
    ]
  },
  {
    "id": 18,
    "question": "你参加赛跑，当你努力超过第2名时，你是第几名？",
    "answer": 1,
    "options": [
      "第2名",
      "第3名",
      "第1名",
      "第4名"
    ]
  },
  {
    "id": 19,
    "question": "蔡依林《布拉格广场》中的布拉格在哪个国家？",
    "answer": 1,
    "options": [
      "捷克",
      "列支敦士登",
      "奥地利",
      "波兰"
    ]
  },
  {
    "id": 20,
    "question": "南斗六星属于哪个星座？",
    "answer": 2,
    "options": [
      "天秤座",
      "人马座",
      "蛇夫座",
      "大熊座"
    ]
  },
  {
    "id": 21,
    "question": "《咏鹅》的作者是初唐四杰中的哪一个？",
    "answer": 4,
    "options": [
      "王勃",
      "杨炯",
      "卢照邻",
      "骆宾王"
    ]
  },
  {
    "id": 22,
    "question": "肯德基是哪年来到中国北京开店的？",
    "answer": 2,
    "options": [
      "1984年",
      "1987年",
      "1986年",
      "1985年"
    ]
  },
  {
    "id": 23,
    "question": "二十四节气中最冷的节气是？",
    "answer": 4,
    "options": [
      "小寒",
      "冬至",
      "霜降",
      "大寒"
    ]
  },
  {
    "id": 24,
    "question": "被称为「杂交水稻之父」的是？",
    "answer": 1,
    "options": [
      "袁隆平",
      "吴振宇",
      "钱学森",
      "杨振宁"
    ]
  },
  {
    "id": 25,
    "question": "诗句「小时不识月」的下一句是？",
    "answer": 4,
    "options": [
      "低头望故乡",
      "又疑瑶台镜",
      "遥望青云山",
      "呼作白玉盘"
    ]
  },
  {
    "id": 26,
    "question": "精酿啤酒风格 IPA 的全称是？",
    "answer": 1,
    "options": [
      "印度淡色艾尔",
      "意大利淡色艾尔",
      "以色列淡色艾尔",
      "爱尔兰淡色艾尔"
    ]
  },
  {
    "id": 27,
    "question": "抗美援朝战争期间中国人民志愿军的总指挥是？",
    "answer": 3,
    "options": [
      "聂荣臻",
      "粟裕",
      "彭德怀",
      "叶向英"
    ]
  },
  {
    "id": 28,
    "question": "二战期间被称为「北非之狐」的将领的国籍是？",
    "answer": 2,
    "options": [
      "埃及",
      "德国",
      "英国",
      "法国"
    ]
  },
  {
    "id": 29,
    "question": "北半球一年当中，黑夜最长的一天可能是哪天？",
    "answer": 3,
    "options": [
      "12月29号",
      "12月27号",
      "12月22号",
      "12月25号"
    ]
  },
  {
    "id": 30,
    "question": "哪个国家的法律禁止蛇在本国出现？",
    "answer": 3,
    "options": [
      "保加利亚",
      "塞浦路斯",
      "新西兰",
      "塞尔维亚"
    ]
  }
]